google/cloud/compute/__init__.py
google/cloud/compute/gapic_version.py
google/cloud/compute/py.typed
google/cloud/compute_v1/__init__.py
google/cloud/compute_v1/gapic_metadata.json
google/cloud/compute_v1/gapic_version.py
google/cloud/compute_v1/py.typed
google/cloud/compute_v1/services/__init__.py
google/cloud/compute_v1/services/accelerator_types/__init__.py
google/cloud/compute_v1/services/accelerator_types/client.py
google/cloud/compute_v1/services/accelerator_types/pagers.py
google/cloud/compute_v1/services/accelerator_types/transports/__init__.py
google/cloud/compute_v1/services/accelerator_types/transports/base.py
google/cloud/compute_v1/services/accelerator_types/transports/rest.py
google/cloud/compute_v1/services/accelerator_types/transports/rest_base.py
google/cloud/compute_v1/services/addresses/__init__.py
google/cloud/compute_v1/services/addresses/client.py
google/cloud/compute_v1/services/addresses/pagers.py
google/cloud/compute_v1/services/addresses/transports/__init__.py
google/cloud/compute_v1/services/addresses/transports/base.py
google/cloud/compute_v1/services/addresses/transports/rest.py
google/cloud/compute_v1/services/addresses/transports/rest_base.py
google/cloud/compute_v1/services/advice/__init__.py
google/cloud/compute_v1/services/advice/client.py
google/cloud/compute_v1/services/advice/transports/__init__.py
google/cloud/compute_v1/services/advice/transports/base.py
google/cloud/compute_v1/services/advice/transports/rest.py
google/cloud/compute_v1/services/advice/transports/rest_base.py
google/cloud/compute_v1/services/autoscalers/__init__.py
google/cloud/compute_v1/services/autoscalers/client.py
google/cloud/compute_v1/services/autoscalers/pagers.py
google/cloud/compute_v1/services/autoscalers/transports/__init__.py
google/cloud/compute_v1/services/autoscalers/transports/base.py
google/cloud/compute_v1/services/autoscalers/transports/rest.py
google/cloud/compute_v1/services/autoscalers/transports/rest_base.py
google_cloud_compute-1.43.0.dist-info/licenses/LICENSE
google_cloud_compute-1.43.0.dist-info/METADATA
google_cloud_compute-1.43.0.dist-info/WHEEL
google_cloud_compute-1.43.0.dist-info/top_level.txt
google_cloud_compute-1.43.0.dist-info/RECORD
